helloworld.py
khatri_pck-0.0.1.dist-info/LICENSE
khatri_pck-0.0.1.dist-info/METADATA
khatri_pck-0.0.1.dist-info/WHEEL
khatri_pck-0.0.1.dist-info/top_level.txt
khatri_pck-0.0.1.dist-info/RECORD
