Metadata-Version: 2.1
Name: khatri-pck
Version: 0.0.1
Summary: Apurva Khatri's first PyPy package
Home-page: https://github.com/apurvakhatri/Khatri-pck/tree/draft1.0
Author: Apurva Khatri
Author-email: apurvakhatri2011@gmail.com
License: UNKNOWN
Platform: UNKNOWN
